hansken_extraction_plugin/__init__.py
hansken_extraction_plugin/api/__init__.py
hansken_extraction_plugin/api/data_context.py
hansken_extraction_plugin/api/extraction_plugin.py
hansken_extraction_plugin/api/extraction_trace.py
hansken_extraction_plugin/api/plugin_info.py
hansken_extraction_plugin/api/search_result.py
hansken_extraction_plugin/api/search_sort_option.py
hansken_extraction_plugin/api/trace_searcher.py
hansken_extraction_plugin/api/tracelet.py
hansken_extraction_plugin/api/transformation.py
hansken_extraction_plugin/api/transformer.py
hansken_extraction_plugin/buildkit/__init__.py
hansken_extraction_plugin/buildkit/build_plugin.py
hansken_extraction_plugin/buildkit/build_plugin_ci.py
hansken_extraction_plugin/buildkit/build_utils.py
hansken_extraction_plugin/buildkit/color_log.py
hansken_extraction_plugin/buildkit/label_plugin.py
hansken_extraction_plugin/buildkit/plugin_info.py
hansken_extraction_plugin/decorators/__init__.py
hansken_extraction_plugin/decorators/transformer.py
hansken_extraction_plugin/framework/DataMessages_pb2.py
hansken_extraction_plugin/framework/DataMessages_pb2.pyi
hansken_extraction_plugin/framework/DataMessages_pb2_grpc.py
hansken_extraction_plugin/framework/ExtractionPluginService_pb2.py
hansken_extraction_plugin/framework/ExtractionPluginService_pb2.pyi
hansken_extraction_plugin/framework/ExtractionPluginService_pb2_grpc.py
hansken_extraction_plugin/framework/Health_pb2.py
hansken_extraction_plugin/framework/Health_pb2.pyi
hansken_extraction_plugin/framework/Health_pb2_grpc.py
hansken_extraction_plugin/framework/PrimitiveMessages_pb2.py
hansken_extraction_plugin/framework/PrimitiveMessages_pb2.pyi
hansken_extraction_plugin/framework/PrimitiveMessages_pb2_grpc.py
hansken_extraction_plugin/framework/RpcCallMessages_pb2.py
hansken_extraction_plugin/framework/RpcCallMessages_pb2.pyi
hansken_extraction_plugin/framework/RpcCallMessages_pb2_grpc.py
hansken_extraction_plugin/framework/__init__.py
hansken_extraction_plugin-0.9.16.dist-info/METADATA
hansken_extraction_plugin-0.9.16.dist-info/WHEEL
hansken_extraction_plugin-0.9.16.dist-info/entry_points.txt
hansken_extraction_plugin-0.9.16.dist-info/top_level.txt
hansken_extraction_plugin-0.9.16.dist-info/RECORD
