Metadata-Version: 2.4
Name: hansken_extraction_plugin
Version: 0.9.16
Summary: Python API to implement Hansken extraction plugins
Home-page: https://netherlandsforensicinstitute.github.io/hansken-extraction-plugin-sdk-documentation/
Author: Netherlands Forensic Institute
Author-email: hansken-support@nfi.nl
License: Apache License, Version 2.0
Classifier: Development Status :: 4 - Beta
Classifier: License :: OSI Approved :: Apache Software License
Classifier: Programming Language :: Python :: 3 :: Only
Classifier: Programming Language :: Python :: 3.10
Classifier: Programming Language :: Python :: 3.11
Classifier: Programming Language :: Python :: 3.12
Classifier: Programming Language :: Python :: 3.13
Requires-Python: >=3.10
Requires-Dist: docker>=7.0.0
Requires-Dist: grpcio>=1.76.0
Requires-Dist: hansken>=2024.4.17
Requires-Dist: logbook>=1.5.3
Requires-Dist: protobuf>=6.31.1
Requires-Dist: pytz>=2023.3
Requires-Dist: typing-extensions>=4.5.0
Dynamic: author
Dynamic: author-email
Dynamic: classifier
Dynamic: home-page
Dynamic: license
Dynamic: requires-dist
Dynamic: requires-python
Dynamic: summary
